{
  "search_metadata": {
    "id": "69bb5ddac29c3d857130caa7",
    "status": "Success",
    "json_endpoint": "https://serpapi.com/searches/jledoujv2ah0irFe-D1l2A/69bb5ddac29c3d857130caa7.json",
    "pixel_position_endpoint": "https://serpapi.com/searches/jledoujv2ah0irFe-D1l2A/69bb5ddac29c3d857130caa7.json_with_pixel_position",
    "created_at": "2026-03-19 02:22:18 UTC",
    "processed_at": "2026-03-19 02:22:18 UTC",
    "google_url": "https://www.google.com/search?q=Roger+Williams+%22US+House+TX-31%22+%22Central+Texas%22+Instagram&oq=Roger+Williams+%22US+House+TX-31%22+%22Central+Texas%22+Instagram&sourceid=chrome&ie=UTF-8",
    "raw_html_file": "https://serpapi.com/searches/jledoujv2ah0irFe-D1l2A/69bb5ddac29c3d857130caa7.html",
    "total_time_taken": 3.78
  },
  "search_parameters": {
    "engine": "google",
    "q": "Roger Williams \"US House TX-31\" \"Central Texas\" Instagram",
    "google_domain": "google.com",
    "device": "desktop"
  },
  "search_information": {
    "query_displayed": "Roger Williams \"US House TX-31\" \"Central Texas\" Instagram",
    "total_results": 316000,
    "time_taken_displayed": 0.69,
    "organic_results_state": "Empty showing fixed spelling results",
    "showing_results_for": "Roger Williams US House TX-31 Central Texas Instagram",
    "spelling_fix": "Roger Williams US House TX-31 Central Texas Instagram"
  },
  "organic_results": [
    {
      "position": 1,
      "title": "Congressman Roger Williams (@reprwilliams)",
      "link": "https://www.instagram.com/reprwilliams/",
      "redirect_link": "https://www.google.com/url?sa=t&source=web&rct=j&opi=89978449&url=https://www.instagram.com/reprwilliams/&ved=2ahUKEwij_oPo86qTAxU1q5UCHXzyGyoQFnoECCMQAQ",
      "displayed_link": "4.6K+ followers",
      "favicon": "https://serpapi.com/searches/69bb5ddac29c3d857130caa7/images/9txljGAlFgI1RckwFo9rKMILq4Db-AYbZx_R8pJdTPE.png",
      "snippet": "4.6K+ followers · 255 following · 375 posts · @reprwilliams: “Fighting for freedom, lower taxes, and less regulations for #TX25.",
      "about_this_result": {
        "source": {
          "description": "4.6K+ followers · 255 following · 375 posts · @reprwilliams: “Fighting for freedom, lower taxes, and less regulations for #TX25.",
          "source_info_link": "https://www.instagram.com/reprwilliams/",
          "icon": "https://serpapi.com/searches/69bb5ddac29c3d857130caa7/images/9txljGAlFgI1RckwFo9rKLubP-NO8NvvpkeQEGCRdn5mfjkmK3rMTpC5ZXHE2w_H.png"
        },
        "languages": [
          "en"
        ],
        "regions": [
          "US"
        ]
      },
      "about_page_link": "https://www.google.com/search?q=About+https://www.instagram.com/reprwilliams/&tbm=ilp",
      "about_page_serpapi_link": "https://serpapi.com/search.json?engine=google_about_this_result&google_domain=google.com&q=About+https%3A%2F%2Fwww.instagram.com%2Freprwilliams%2F",
      "missing": [
        "Central"
      ],
      "must_include": {
        "word": "Central",
        "link": "https://www.google.com/search?sca_esv=c2ca9e7198039ef3&q=Roger+Williams+US+House+TX-31+%22Central%22+Texas+Instagram&sa=X&ved=2ahUKEwij_oPo86qTAxU1q5UCHXzyGyoQ5t4CegQIMBAB"
      },
      "source": "Instagram · reprwilliams"
    },
    {
      "position": 2,
      "title": "Congressman Roger Williams (@reprwilliams)",
      "link": "https://www.instagram.com/RepRWilliams/?__d=1%2F%2F",
      "redirect_link": "https://www.google.com/url?sa=t&source=web&rct=j&opi=89978449&url=https://www.instagram.com/RepRWilliams/%3F__d%3D1%252F%252F&ved=2ahUKEwij_oPo86qTAxU1q5UCHXzyGyoQFnoECCUQAQ",
      "displayed_link": "https://www.instagram.com › RepRWilliams",
      "favicon": "https://serpapi.com/searches/69bb5ddac29c3d857130caa7/images/9txljGAlFgI1RckwFo9rKCN-5oAbGy25_Z4ocsYwcd8.png",
      "snippet": "4444 Followers, 247 Following, 317 Posts - Congressman Roger Williams (@RepRWilliams) on Instagram: \"Fighting for freedom, lower taxes, and less regulations ...",
      "snippet_highlighted_words": [
        "Roger Williams",
        "Instagram"
      ],
      "about_this_result": {
        "source": {
          "description": "4444 Followers, 247 Following, 317 Posts - Congressman Roger Williams (@RepRWilliams) on Instagram: \"Fighting for freedom, lower taxes, and less regulations ...",
          "source_info_link": "https://www.instagram.com/RepRWilliams/?__d=1%2F%2F",
          "icon": "https://serpapi.com/searches/69bb5ddac29c3d857130caa7/images/9txljGAlFgI1RckwFo9rKEA1WOsqke--pZqLR1CKK_mCI6pAdtAX0i-qJVNqMQDw.png"
        },
        "languages": [
          "en"
        ],
        "regions": [
          "US"
        ]
      },
      "about_page_link": "https://www.google.com/search?q=About+https://www.instagram.com/RepRWilliams/?__d=1%2F%2F&tbm=ilp",
      "about_page_serpapi_link": "https://serpapi.com/search.json?engine=google_about_this_result&google_domain=google.com&q=About+https%3A%2F%2Fwww.instagram.com%2FRepRWilliams%2F%3F__d%3D1%252F%252F",
      "missing": [
        "31",
        "Central"
      ],
      "source": "Instagram"
    },
    {
      "position": 3,
      "title": "Congressman Roger Williams (@reprwilliams)",
      "link": "https://www.instagram.com/RepRWilliams/?__d=1%252F",
      "redirect_link": "https://www.google.com/url?sa=t&source=web&rct=j&opi=89978449&url=https://www.instagram.com/RepRWilliams/%3F__d%3D1%25252F&ved=2ahUKEwij_oPo86qTAxU1q5UCHXzyGyoQFnoECB4QAQ",
      "displayed_link": "https://www.instagram.com › RepRWilliams",
      "favicon": "https://serpapi.com/searches/69bb5ddac29c3d857130caa7/images/9txljGAlFgI1RckwFo9rKHFfBlpwyYY45QElx8HmIwA.png",
      "snippet": "4423 Followers, 241 Following, 313 Posts - Congressman Roger Williams (@RepRWilliams) on Instagram: \"Fighting for freedom, lower taxes, and less regulations ...",
      "snippet_highlighted_words": [
        "Roger Williams",
        "Instagram"
      ],
      "about_this_result": {
        "source": {
          "description": "4423 Followers, 241 Following, 313 Posts - Congressman Roger Williams (@RepRWilliams) on Instagram: \"Fighting for freedom, lower taxes, and less regulations ...",
          "source_info_link": "https://www.instagram.com/RepRWilliams/?__d=1%252F",
          "icon": "https://serpapi.com/searches/69bb5ddac29c3d857130caa7/images/9txljGAlFgI1RckwFo9rKINIDAih_IfWmQ3kMDnhOecSj683wpDTkpIg4RaxpiTt.png"
        },
        "languages": [
          "en"
        ],
        "regions": [
          "US"
        ]
      },
      "about_page_link": "https://www.google.com/search?q=About+https://www.instagram.com/RepRWilliams/?__d=1%252F&tbm=ilp",
      "about_page_serpapi_link": "https://serpapi.com/search.json?engine=google_about_this_result&google_domain=google.com&q=About+https%3A%2F%2Fwww.instagram.com%2FRepRWilliams%2F%3F__d%3D1%25252F",
      "missing": [
        "31",
        "Central"
      ],
      "source": "Instagram"
    },
    {
      "position": 4,
      "title": "Congressman Roger Williams (@reprwilliams)",
      "link": "https://www.instagram.com/reprwilliams/reels/",
      "redirect_link": "https://www.google.com/url?sa=t&source=web&rct=j&opi=89978449&url=https://www.instagram.com/reprwilliams/reels/&ved=2ahUKEwij_oPo86qTAxU1q5UCHXzyGyoQFnoECCAQAQ",
      "displayed_link": "https://www.instagram.com › reprwilliams",
      "favicon": "https://serpapi.com/searches/69bb5ddac29c3d857130caa7/images/9txljGAlFgI1RckwFo9rKCauFD32j1TPjn10lzxIq1I.png",
      "snippet": "4.5K+ followers · 253 following · 331 posts · @reprwilliams: “Fighting for freedom, lower taxes, and less regulations for #TX25.",
      "about_this_result": {
        "source": {
          "description": "4.5K+ followers · 253 following · 331 posts · @reprwilliams: “Fighting for freedom, lower taxes, and less regulations for #TX25.",
          "source_info_link": "https://www.instagram.com/reprwilliams/reels/",
          "icon": "https://serpapi.com/searches/69bb5ddac29c3d857130caa7/images/9txljGAlFgI1RckwFo9rKOVYK5_FqOjcXPpZKaYbVesWlXJXfFDFTTAf2wgk0jL0.png"
        },
        "languages": [
          "en"
        ],
        "regions": [
          "US"
        ]
      },
      "about_page_link": "https://www.google.com/search?q=About+https://www.instagram.com/reprwilliams/reels/&tbm=ilp",
      "about_page_serpapi_link": "https://serpapi.com/search.json?engine=google_about_this_result&google_domain=google.com&q=About+https%3A%2F%2Fwww.instagram.com%2Freprwilliams%2Freels%2F",
      "missing": [
        "US",
        "House",
        "TX-",
        "31",
        "Central",
        "Texas"
      ],
      "source": "Instagram"
    },
    {
      "position": 5,
      "title": "I look forward to our continued work in Making America ...",
      "link": "https://www.instagram.com/p/DVRl0bID7ao/",
      "redirect_link": "https://www.google.com/url?sa=t&source=web&rct=j&opi=89978449&url=https://www.instagram.com/p/DVRl0bID7ao/&ved=2ahUKEwij_oPo86qTAxU1q5UCHXzyGyoQFnoECCIQAQ",
      "displayed_link": "20+ likes · 2 weeks ago",
      "favicon": "https://serpapi.com/searches/69bb5ddac29c3d857130caa7/images/9txljGAlFgI1RckwFo9rKJchaAwb7GEmAw0-nErnMCY.png",
      "snippet": "Trump @realDonaldTrump Congressman Roger Williams is a Tremendous Champion for the incredible people of Texas' 25th Congressional District!",
      "snippet_highlighted_words": [
        "Roger Williams",
        "Texas",
        "Congressional"
      ],
      "about_this_result": {
        "source": {
          "description": "Trump @realDonaldTrump Congressman Roger Williams is a Tremendous Champion for the incredible people of Texas' 25th Congressional District!",
          "source_info_link": "https://www.instagram.com/p/DVRl0bID7ao/",
          "icon": "https://serpapi.com/searches/69bb5ddac29c3d857130caa7/images/9txljGAlFgI1RckwFo9rKJUo_vA1LxjURDVmieayiaTVRivNw5HlbU6Svr1_RPc9.png"
        },
        "languages": [
          "en"
        ],
        "regions": [
          "US"
        ]
      },
      "about_page_link": "https://www.google.com/search?q=About+https://www.instagram.com/p/DVRl0bID7ao/&tbm=ilp",
      "about_page_serpapi_link": "https://serpapi.com/search.json?engine=google_about_this_result&google_domain=google.com&q=About+https%3A%2F%2Fwww.instagram.com%2Fp%2FDVRl0bID7ao%2F",
      "missing": [
        "Central"
      ],
      "must_include": {
        "word": "Central",
        "link": "https://www.google.com/search?sca_esv=c2ca9e7198039ef3&q=Roger+Williams+US+House+TX-31+%22Central%22+Texas+Instagram&sa=X&ved=2ahUKEwij_oPo86qTAxU1q5UCHXzyGyoQ5t4CegQIMhAB"
      },
      "source": "Instagram · reprwilliams"
    },
    {
      "position": 6,
      "title": "“If you give small businesses the opportunity to succeed, they ...",
      "link": "https://www.instagram.com/reel/DVy_dCFCW1S/",
      "displayed_link": "8 likes · 6 days ago",
      "thumbnail": "https://serpapi.com/searches/69bb5ddac29c3d857130caa7/images/9txljGAlFgI1RckwFo9rKAabkSLCiOOZKjJYCECOMM0.jpeg",
      "favicon": "https://serpapi.com/searches/69bb5ddac29c3d857130caa7/images/9txljGAlFgI1RckwFo9rKHWpJotQkLRuTZO__1DKy0Q.png",
      "snippet": "I'm Congressman Roger Williams representing the 25th district here in the great state of Texas and today, I'm at the ballpark in Arlington ...",
      "duration": "0:35",
      "about_this_result": {
        "source": {
          "description": "I'm Congressman Roger Williams representing the 25th district here in the great state of Texas and today, I'm at the ballpark in Arlington ...",
          "source_info_link": "https://www.instagram.com/reel/DVy_dCFCW1S/",
          "icon": "https://serpapi.com/searches/69bb5ddac29c3d857130caa7/images/9txljGAlFgI1RckwFo9rKADGRj8whVRiSlgZZpqEeLuwZoXgzeiIUR0gbiJwyFjp.png"
        }
      },
      "about_page_link": "https://www.google.com/search?q=About+https://www.instagram.com/reel/DVy_dCFCW1S/&tbm=ilp",
      "about_page_serpapi_link": "https://serpapi.com/search.json?engine=google_about_this_result&google_domain=google.com&q=About+https%3A%2F%2Fwww.instagram.com%2Freel%2FDVy_dCFCW1S%2F",
      "missing": [
        "TX-",
        "31"
      ],
      "source": "Instagram · housesmallbiz"
    },
    {
      "position": 7,
      "title": "I had a productive meeting with the Texas Rural Water ...",
      "link": "https://www.instagram.com/p/DUlMTeiERXw/",
      "redirect_link": "https://www.google.com/url?sa=t&source=web&rct=j&opi=89978449&url=https://www.instagram.com/p/DUlMTeiERXw/&ved=2ahUKEwij_oPo86qTAxU1q5UCHXzyGyoQFnoECCEQAQ",
      "displayed_link": "4 likes · 1 month ago",
      "favicon": "https://serpapi.com/searches/69bb5ddac29c3d857130caa7/images/9txljGAlFgI1RckwFo9rKBuw-tPEngTMDn5Mit2oh9E.png",
      "snippet": "Photo by Congressman Vicente Gonzalez on February 03, 2026. May be an image of.",
      "about_this_result": {
        "source": {
          "description": "Photo by Congressman Vicente Gonzalez on February 03, 2026. May be an image of.",
          "source_info_link": "https://www.instagram.com/p/DUlMTeiERXw/",
          "icon": "https://serpapi.com/searches/69bb5ddac29c3d857130caa7/images/9txljGAlFgI1RckwFo9rKPQmWr7k_3PxaaK_9JYOjNddJ6xNntoKY29GJPN9-GKn.png"
        },
        "languages": [
          "en"
        ],
        "regions": [
          "US"
        ]
      },
      "about_page_link": "https://www.google.com/search?q=About+https://www.instagram.com/p/DUlMTeiERXw/&tbm=ilp",
      "about_page_serpapi_link": "https://serpapi.com/search.json?engine=google_about_this_result&google_domain=google.com&q=About+https%3A%2F%2Fwww.instagram.com%2Fp%2FDUlMTeiERXw%2F",
      "source": "Instagram · reprwilliams"
    },
    {
      "position": 8,
      "title": "A visit with Congressman Roger Williams in Stephenville ...",
      "link": "https://www.instagram.com/p/DN9HbrsDbfk/",
      "redirect_link": "https://www.google.com/url?sa=t&source=web&rct=j&opi=89978449&url=https://www.instagram.com/p/DN9HbrsDbfk/&ved=2ahUKEwij_oPo86qTAxU1q5UCHXzyGyoQFnoECEAQAQ",
      "displayed_link": "8 likes · 6 months ago",
      "favicon": "https://serpapi.com/searches/69bb5ddac29c3d857130caa7/images/9txljGAlFgI1RckwFo9rKJg-fm6-55kUc-BIlfjOlOU.png",
      "snippet": "week the Texas Farm Bureau organized a roundtable discussion with U.S. Congressman Roger Williams and agricultural industries from across ...",
      "snippet_highlighted_words": [
        "Texas",
        "U.S.",
        "Roger Williams"
      ],
      "about_this_result": {
        "source": {
          "description": "week the Texas Farm Bureau organized a roundtable discussion with U.S. Congressman Roger Williams and agricultural industries from across ...",
          "source_info_link": "https://www.instagram.com/p/DN9HbrsDbfk/",
          "icon": "https://serpapi.com/searches/69bb5ddac29c3d857130caa7/images/9txljGAlFgI1RckwFo9rKNw4rBYOsMrkELGoRJy2KxMJIbmfRWBTE_4aimGOt_Gk.png"
        },
        "languages": [
          "en"
        ],
        "regions": [
          "US"
        ]
      },
      "about_page_link": "https://www.google.com/search?q=About+https://www.instagram.com/p/DN9HbrsDbfk/&tbm=ilp",
      "about_page_serpapi_link": "https://serpapi.com/search.json?engine=google_about_this_result&google_domain=google.com&q=About+https%3A%2F%2Fwww.instagram.com%2Fp%2FDN9HbrsDbfk%2F",
      "missing": [
        "Central"
      ],
      "must_include": {
        "word": "Central",
        "link": "https://www.google.com/search?sca_esv=c2ca9e7198039ef3&q=Roger+Williams+US+House+TX-31+%22Central%22+Texas+Instagram&sa=X&ved=2ahUKEwij_oPo86qTAxU1q5UCHXzyGyoQ5t4CegQIQhAB"
      },
      "source": "Instagram · texaspecangrowers"
    },
    {
      "position": 9,
      "title": "Congressman Roger Williams Office",
      "link": "https://www.instagram.com/explore/locations/134234929/congressman-roger-williams-office/",
      "redirect_link": "https://www.google.com/url?sa=t&source=web&rct=j&opi=89978449&url=https://www.instagram.com/explore/locations/134234929/congressman-roger-williams-office/&ved=2ahUKEwij_oPo86qTAxU1q5UCHXzyGyoQFnoECDcQAQ",
      "displayed_link": "https://www.instagram.com › explore › locations › con...",
      "favicon": "https://serpapi.com/searches/69bb5ddac29c3d857130caa7/images/9txljGAlFgI1RckwFo9rKMrdaBWTOiZz5zTo0cxX8Ik.png",
      "snippet": "See photos and videos taken at this location and explore places nearby.",
      "about_this_result": {
        "source": {
          "description": "See photos and videos taken at this location and explore places nearby.",
          "source_info_link": "https://www.instagram.com/explore/locations/134234929/congressman-roger-williams-office/",
          "icon": "https://serpapi.com/searches/69bb5ddac29c3d857130caa7/images/9txljGAlFgI1RckwFo9rKCNLEm2GS8EXAt5nu39M58nbFM-s7raTIRIWsvj7K2_0.png"
        },
        "languages": [
          "en"
        ],
        "regions": [
          "US"
        ]
      },
      "about_page_link": "https://www.google.com/search?q=About+https://www.instagram.com/explore/locations/134234929/congressman-roger-williams-office/&tbm=ilp",
      "about_page_serpapi_link": "https://serpapi.com/search.json?engine=google_about_this_result&google_domain=google.com&q=About+https%3A%2F%2Fwww.instagram.com%2Fexplore%2Flocations%2F134234929%2Fcongressman-roger-williams-office%2F",
      "missing": [
        "US",
        "House",
        "TX-",
        "31",
        "Central",
        "Texas"
      ],
      "source": "Instagram"
    },
    {
      "position": 10,
      "title": "Rep Roger Williams (R-TX) for a piece with @scottwongdc ...",
      "link": "https://www.instagram.com/p/Cz8-vqbL_FT/",
      "redirect_link": "https://www.google.com/url?sa=t&source=web&rct=j&opi=89978449&url=https://www.instagram.com/p/Cz8-vqbL_FT/&ved=2ahUKEwij_oPo86qTAxU1q5UCHXzyGyoQFnoECDgQAQ",
      "displayed_link": "360+ likes · 2 years ago",
      "favicon": "https://serpapi.com/searches/69bb5ddac29c3d857130caa7/images/9txljGAlFgI1RckwFo9rKPMGpT6s80rNpspb-SJwqpA.png",
      "snippet": "368 likes, 1 comments - frankthorpv on November 22, 2023: \"Rep Roger Williams (R-TX) for a piece with @scottwongdc about how, as a child, ...",
      "snippet_highlighted_words": [
        "Roger Williams",
        "TX"
      ],
      "about_this_result": {
        "source": {
          "description": "368 likes, 1 comments - frankthorpv on November 22, 2023: \"Rep Roger Williams (R-TX) for a piece with @scottwongdc about how, as a child, ...",
          "source_info_link": "https://www.instagram.com/p/Cz8-vqbL_FT/",
          "icon": "https://serpapi.com/searches/69bb5ddac29c3d857130caa7/images/9txljGAlFgI1RckwFo9rKJA_9eQIGs0R5oM0joGmUBVQgIRUKPPnqN029Yx9cuK4.png"
        },
        "languages": [
          "en"
        ],
        "regions": [
          "US"
        ]
      },
      "about_page_link": "https://www.google.com/search?q=About+https://www.instagram.com/p/Cz8-vqbL_FT/&tbm=ilp",
      "about_page_serpapi_link": "https://serpapi.com/search.json?engine=google_about_this_result&google_domain=google.com&q=About+https%3A%2F%2Fwww.instagram.com%2Fp%2FCz8-vqbL_FT%2F",
      "missing": [
        "31",
        "Central",
        "Texas"
      ],
      "source": "Instagram · frankthorpv"
    }
  ],
  "pagination": {
    "current": 1,
    "next": "https://www.google.com/search?q=Roger+Williams+US+House+TX-31+Central+Texas+Instagram&sca_esv=c2ca9e7198039ef3&ei=3V27aeObDrXW1sQP_OTv0AI&start=10&sa=N&sstk=Af77f_dHOYY5PILTIO2GW-3tlHAWChSaIrE1jZ3VcHT0AIuUemsm2EGBcr6Sw7WrpPVdr3AjEVIz_AK3zFTBTz8S0V6oJl-9rpxhVg&ved=2ahUKEwij_oPo86qTAxU1q5UCHXzyGyoQ8NMDegQIChAG",
    "other_pages": {
      "2": "https://www.google.com/search?q=Roger+Williams+US+House+TX-31+Central+Texas+Instagram&sca_esv=c2ca9e7198039ef3&ei=3V27aeObDrXW1sQP_OTv0AI&start=10&sa=N&sstk=Af77f_dHOYY5PILTIO2GW-3tlHAWChSaIrE1jZ3VcHT0AIuUemsm2EGBcr6Sw7WrpPVdr3AjEVIz_AK3zFTBTz8S0V6oJl-9rpxhVg&ved=2ahUKEwij_oPo86qTAxU1q5UCHXzyGyoQ8tMDegQIChAE"
    }
  },
  "serpapi_pagination": {
    "current": 1,
    "next_link": "https://serpapi.com/search.json?device=desktop&engine=google&google_domain=google.com&q=Roger+Williams+US+House+TX-31+Central+Texas+Instagram&start=10",
    "next": "https://serpapi.com/search.json?device=desktop&engine=google&google_domain=google.com&q=Roger+Williams+US+House+TX-31+Central+Texas+Instagram&start=10",
    "other_pages": {
      "2": "https://serpapi.com/search.json?device=desktop&engine=google&google_domain=google.com&q=Roger+Williams+US+House+TX-31+Central+Texas+Instagram&start=10"
    }
  }
}